[
    {
        "name": "OG Trilogy",
        "levels": [
            "Mortiferus Step",
            "On the grid",
            "14 Wave"
        ],
        "colour": "linear-gradient(90deg, rgba(0,53,250,1) 0%, rgba(0,24,97,1) 50%, rgba(0,53,250,1) 100%)"
    },
    {
        "name": "ItzLucie Pack",
        "levels": [
            "Vehemens Mortialis",
            "Arid Maze",
            "Mortiferus Step"
        ],
        "colour": "linear-gradient(90deg, rgba(34,250,0,1) 0%, rgba(24,97,0,1) 50%, rgba(53,250,0,1) 100%)"
    },
    {
        "name": "ItzLucie Pack II",
        "levels": [
            "The Lightning Chode",
            "The Sepulcher",
            "hole"
        ],
        "colour": "linear-gradient(90deg, rgba(34,200,0,1) 0%, rgba(24,67,0,1) 50%, rgba(53,200,0,1) 100%)"
    },
    {
        "name": "Top 1 Pack",
        "levels": [
            "Cesium 137",
            "Vehemens Mortialis",
            "Mortiferus Step",
            "On the grid"
        ],
        "colour": "linear-gradient(90deg, rgba(250,34,0,1) 0%, rgba(97,24,0,1) 50%, rgba(250,53,0,1) 100%)"
    },
    {
        "name": "Chokepoint Pack",
        "levels": [
            "Gladus",
            "The Lightning Chode",
            "the janus curse",
            "Bazinga"
        ],
        "colour": "linear-gradient(90deg, rgba(250,230,0,1) 0%, rgba(97,78,0,1) 50%, rgba(250,150,0,1) 100%)"
    },
    {
        "name": "Adhafera Slop Pack",
        "levels": [
            "trep",
            "the poop of ryan",
            "the janus curse"
        ],
        "colour": "linear-gradient(90deg, rgba(88,57,39,1) 0%, rgba(88,57,39,1) 50%, rgba(88,57,39,1) 100%)"
    },
    {
        "name": "trme pack",
        "levels": [
            "On the grid",
            "okaaay",
            "Bazinga"
        ],
        "colour": "linear-gradient(90deg, rgba(0,255,255,1) 0%, rgba(0,90,140,1) 50%, rgba(0,255,255,1) 100%)"
    },
    {
        "name": "Unplaceable",
        "levels": [
            "trep",
            "Arid Maze",
            "14 Wave"
        ],
        "colour": "linear-gradient(90deg, rgba(255,255,255,1) 0%, rgba(130,130,130,1) 50%, rgba(255,255,255,1) 100%)"
    },
    {
        "name": "VmoapX Pack",
        "levels": [
            "Luminous Chaos",
            "Yahweh",
            "Compacted Torment"
        ],
        "colour": "linear-gradient(90deg, rgba(255,0,255,1) 0%, rgba(130,0,130,1) 50%, rgba(255,0,255,1) 100%)"
    },
    {
        "name": "Ship Carried Pack",
        "levels": [
            "Luminous Chaos",
            "the poop of ryan",
            "dont play this"
        ],
        "colour": "linear-gradient(90deg, rgba(145,0,200,1) 0%, rgba(175,0,230,1) 50%, rgba(145,0,200,1) 100%)"
    }
]
